dataclass.py
dataclas-0.9.3.dist-info/LICENSE
dataclas-0.9.3.dist-info/METADATA
dataclas-0.9.3.dist-info/WHEEL
dataclas-0.9.3.dist-info/top_level.txt
dataclas-0.9.3.dist-info/RECORD
