Metadata-Version: 2.1
Name: dataclas
Version: 0.9.3
Summary: Slightly improved dataclasses, backward compatible
Home-page: https://github.com/rec/dataclass
Author: Tom Ritchford
Author-email: tom@swirly.com
License: MIT
Keywords: dataclass
Platform: UNKNOWN
Classifier: Development Status :: 5 - Production/Stable
Classifier: Programming Language :: Python :: 3.7
Classifier: Programming Language :: Python :: 3.8
Classifier: Programming Language :: Python :: 3.9
Classifier: Programming Language :: Python :: 3.10
Classifier: Intended Audience :: Developers
Classifier: License :: OSI Approved :: MIT License
Classifier: Topic :: Software Development :: Libraries
Classifier: Topic :: Utilities
License-File: LICENSE
